{
  "name": "Message",
  "fields": [
    {
      "fieldName": "text",
      "fieldType": "String",
      "fieldValidateRules": ["required"]
    },
    {
      "fieldName": "description",
      "fieldType": "String"
    }
  ],
  "relationships": [],
  "changelogDate": "20201104180838",
  "javadoc": "System messages.\\n@author Isaac Miranda",
  "entityTableName": "message",
  "dto": "mapstruct",
  "pagination": "pagination",
  "service": "serviceClass",
  "jpaMetamodelFiltering": true,
  "fluentMethods": true,
  "readOnly": false,
  "embedded": false,
  "clientRootFolder": "",
  "applications": ["Shopped"]
}
